fileflow/__init__.py
fileflow/config.py
fileflow/file.py
fileflow/util.py
fileflow/workflow.py
fileflow-0.3.dist-info/LICENSE
fileflow-0.3.dist-info/METADATA
fileflow-0.3.dist-info/WHEEL
fileflow-0.3.dist-info/top_level.txt
fileflow-0.3.dist-info/RECORD
