Metadata-Version: 2.1
Name: fileflow
Version: 0.3
Summary: File processing pipelines without boilerplate
Home-page: https://github.com/tfiers/fileflow
Author: Tomas Fiers
Author-email: tomas.fiers@gmail.com
License: UNKNOWN
Project-URL: Source Code, https://github.com/tfiers/fileflow
Platform: UNKNOWN
Classifier: License :: OSI Approved :: MIT License
Classifier: Programming Language :: Python :: 3
Classifier: Operating System :: OS Independent
Requires-Dist: typeguard (~=2.2.2)
Requires-Dist: gitpython (~=2.1.11)
Requires-Dist: decopatch (~=1.4.5)
